getphylo/__init__.py
getphylo/__main__.py
getphylo/align.py
getphylo/extract.py
getphylo/main.py
getphylo/parser.py
getphylo/screen.py
getphylo/trees.py
getphylo/ext/__init__.py
getphylo/ext/diamond.py
getphylo/ext/fasttree.py
getphylo/ext/iqtree.py
getphylo/ext/muscle.py
getphylo/utils/__init__.py
getphylo/utils/checkpoint.py
getphylo/utils/errors.py
getphylo/utils/io.py
getphylo-1.0.1.dist-info/licenses/LICENSE
getphylo-1.0.1.dist-info/METADATA
getphylo-1.0.1.dist-info/WHEEL
getphylo-1.0.1.dist-info/entry_points.txt
getphylo-1.0.1.dist-info/top_level.txt
getphylo-1.0.1.dist-info/RECORD
