Metadata-Version: 2.4
Name: getphylo
Version: 1.0.1
Summary: a python package for automated generation of heuristic phylogenetic trees from genbank files
Home-page: https://github.com/DrBoothTJ/getphylo
Author: Thomas J. Booth
Author-email: thoboo@biosustain.dtu.dk
License: GNU General Public License v3.0
Requires-Python: >=3.7
License-File: LICENSE
Requires-Dist: Bio>=1.7
Dynamic: author
Dynamic: author-email
Dynamic: description
Dynamic: description-content-type
Dynamic: home-page
Dynamic: license
Dynamic: license-file
Dynamic: requires-dist
Dynamic: requires-python
Dynamic: summary
